pylint_calisthenics/__init__.py
pylint_calisthenics/first_class_collections.py
pylint_calisthenics/no_else.py
pylint_calisthenics/no_properties.py
pylint_calisthenics/one_dot_per_line.py
pylint_calisthenics/small_entities.py
pylint_calisthenics/two_instance_variables.py
pylint_calisthenics-0.1.0.dist-info/WHEEL
pylint_calisthenics-0.1.0.dist-info/METADATA
pylint_calisthenics-0.1.0.dist-info/RECORD
