Metadata-Version: 2.1
Name: pylint-calisthenics
Version: 0.1.0
Summary: Implements Object Calisthenics for pylint
License: BSD
Author-email: Miguel Angel Garcia <miguelangel.garcia@gmail.com>
Requires-Python: >=3.9
Requires-Dist: six>=1.16.0
